LICENSE
MANIFEST.in
README.md
pyproject.toml
setup.cfg
setup.py
wagtail_editorjs/__init__.py
wagtail_editorjs/apps.py
wagtail_editorjs/blocks.py
wagtail_editorjs/django_editor.py
wagtail_editorjs/fields.py
wagtail_editorjs/forms.py
wagtail_editorjs/hooks.py
wagtail_editorjs/render.py
wagtail_editorjs/settings.py
wagtail_editorjs.egg-info/PKG-INFO
wagtail_editorjs.egg-info/SOURCES.txt
wagtail_editorjs.egg-info/dependency_links.txt
wagtail_editorjs.egg-info/requires.txt
wagtail_editorjs.egg-info/top_level.txt
wagtail_editorjs/features/__init__.py
wagtail_editorjs/features/blocks.py
wagtail_editorjs/features/documents.py
wagtail_editorjs/features/images.py
wagtail_editorjs/features/inlines.py
wagtail_editorjs/features/lists.py
wagtail_editorjs/features/tunes.py
wagtail_editorjs/migrations/__init__.py
wagtail_editorjs/migrations/__pycache__/__init__.cpython-311.pyc
wagtail_editorjs/registry/__init__.py
wagtail_editorjs/registry/feature_registry.py
wagtail_editorjs/registry/value.py
wagtail_editorjs/registry/element/__init__.py
wagtail_editorjs/registry/element/attrs.py
wagtail_editorjs/registry/element/element.py
wagtail_editorjs/registry/element/utils.py
wagtail_editorjs/registry/features/__init__.py
wagtail_editorjs/registry/features/base.py
wagtail_editorjs/registry/features/basic.py
wagtail_editorjs/registry/features/inlines.py
wagtail_editorjs/registry/features/snippets_inlines.py
wagtail_editorjs/registry/features/view.py
wagtail_editorjs/static/wagtail_editorjs/css/editorjs-widget.css
wagtail_editorjs/static/wagtail_editorjs/css/frontend.css
wagtail_editorjs/static/wagtail_editorjs/js/editorjs-block.js
wagtail_editorjs/static/wagtail_editorjs/js/editorjs-widget-controller.js
wagtail_editorjs/static/wagtail_editorjs/js/editorjs-widget.js
wagtail_editorjs/static/wagtail_editorjs/js/init/drag-drop.js
wagtail_editorjs/static/wagtail_editorjs/js/init/undo-redo.js
wagtail_editorjs/static/wagtail_editorjs/js/tools/attaches.js
wagtail_editorjs/static/wagtail_editorjs/js/tools/wagtail-block-tool.js
wagtail_editorjs/static/wagtail_editorjs/js/tools/wagtail-block.js
wagtail_editorjs/static/wagtail_editorjs/js/tools/wagtail-button-tool.js
