Metadata-Version: 2.1
Name: wagtail-editorjs
Version: 1.6.6
Summary: EditorJS as a widget for Wagtail, with Page- and Image chooser support
Home-page: https://github.com/Nigel2392/wagtail_editorjs
Author: Nigel
Author-email: nigel@goodadvice.it
License: GPL-3.0-only
Classifier: Environment :: Web Environment
Classifier: Framework :: Django
Classifier: Framework :: Django :: 4.2
Classifier: Framework :: Wagtail
Classifier: Framework :: Wagtail :: 5
Classifier: Framework :: Wagtail :: 6
Classifier: Intended Audience :: Developers
Classifier: License :: OSI Approved :: GNU General Public License v3 or later (GPLv3+)
Classifier: Operating System :: OS Independent
Classifier: Programming Language :: Python
Classifier: Programming Language :: Python :: 3
Classifier: Programming Language :: Python :: 3 :: Only
Classifier: Programming Language :: Python :: 3.8
Classifier: Programming Language :: Python :: 3.9
Classifier: Topic :: Internet :: WWW/HTTP
Classifier: Topic :: Internet :: WWW/HTTP :: Dynamic Content
Requires-Python: >=3.8
License-File: LICENSE
